dasosdemo/__init__.py
dasosdemo/common.py
dasosdemo/dasosdemo.py
dasosdemo-0.0.2.dist-info/LICENSE
dasosdemo-0.0.2.dist-info/METADATA
dasosdemo-0.0.2.dist-info/WHEEL
dasosdemo-0.0.2.dist-info/top_level.txt
dasosdemo-0.0.2.dist-info/RECORD
