Metadata-Version: 2.1
Name: dasosdemo
Version: 0.0.2
Summary: My first Python package.
Home-page: https://github.com/kriskaran/dasosdemo
Author: Christoforos Karanikas
Author-email: christoforoskaranikas@yahoo.gr
License: MIT license
Keywords: dasosdemo
Classifier: Intended Audience :: Developers
Classifier: License :: OSI Approved :: MIT License
Classifier: Natural Language :: English
Classifier: Programming Language :: Python :: 3
Classifier: Programming Language :: Python :: 3.8
Classifier: Programming Language :: Python :: 3.9
Classifier: Programming Language :: Python :: 3.10
Classifier: Programming Language :: Python :: 3.11
Requires-Python: >=3.8
License-File: LICENSE
